thzhashmap/hashmap.cp38-win_amd64.pyd
ThzHashMap-1.0.6.dist-info/METADATA
ThzHashMap-1.0.6.dist-info/WHEEL
ThzHashMap-1.0.6.dist-info/top_level.txt
ThzHashMap-1.0.6.dist-info/RECORD
