Metadata-Version: 2.1
Name: ThzHashMap
Version: 1.0.6
Summary: 由天狐宗开发的哈希表，仅供学习
Home-page: https://github.com/tianhuzong/hashmap
Author: Sen
Author-email: tianhuzong@qq.com
License: MIT
Platform: UNKNOWN
Classifier: Development Status :: 5 - Production/Stable
Classifier: License :: OSI Approved :: MIT License
Classifier: Programming Language :: Cython
Classifier: Programming Language :: C++
Classifier: Programming Language :: Python :: 3
Requires-Dist: Cython
